LICENSE
README.md
setup.cfg
setup.py
Flask_APIAlchemy.egg-info/PKG-INFO
Flask_APIAlchemy.egg-info/SOURCES.txt
Flask_APIAlchemy.egg-info/dependency_links.txt
Flask_APIAlchemy.egg-info/not-zip-safe
Flask_APIAlchemy.egg-info/requires.txt
Flask_APIAlchemy.egg-info/top_level.txt
flask_apialchemy/__init__.py