Metadata-Version: 2.1
Name: Flask-APIAlchemy
Version: 1.1.0
Summary: Adds APIAlchemy support to your Flask application, modeled after Flask-SQLAlchemy.
Home-page: https://github.com/homedepot/flask-apialchemy
Author: Mike Phillipson
Author-email: MICHAEL_PHILLIPSON1@homedepot.com
License: BSD-3-Clause
Platform: UNKNOWN
License-File: LICENSE
